dualdesc/__init__.py
dualdesc/py.typed
dualdesc-0.2.0.dist-info/LICENSE
dualdesc-0.2.0.dist-info/METADATA
dualdesc-0.2.0.dist-info/WHEEL
dualdesc-0.2.0.dist-info/top_level.txt
dualdesc-0.2.0.dist-info/RECORD
