Metadata-Version: 2.1
Name: dualdesc
Version: 0.2.0
Summary: Dual description of polytopes.
Home-page: https://gitlab.com/valtron/dualdesc
Author: valtron
Classifier: Programming Language :: Python :: 3 :: Only
Classifier: Programming Language :: Python :: 3.9
Classifier: Programming Language :: Python :: 3.10
Classifier: Operating System :: OS Independent
Classifier: License :: OSI Approved :: GNU Lesser General Public License v3 or later (LGPLv3+)
Requires-Python: >=3.9
License-File: LICENSE
Requires-Dist: pyparma (~=0.5.0)
Requires-Dist: numpy (~=1.25.2)
